nonebot/adapters/opqbot/__init__.py
nonebot/adapters/opqbot/adapter.py
nonebot/adapters/opqbot/bot.py
nonebot/adapters/opqbot/config.py
nonebot/adapters/opqbot/event.py
nonebot/adapters/opqbot/log.py
nonebot/adapters/opqbot/message.py
nonebot/adapters/opqbot/models/__init__.py
nonebot/adapters/opqbot/models/context.py
nonebot/adapters/opqbot/models/message.py
nonebot/adapters/opqbot/models/response.py
nonebot/adapters/opqbot/utils.py
nonebot_adapter_opqbot-0.1.2.dist-info/LICENSE
nonebot_adapter_opqbot-0.1.2.dist-info/METADATA
nonebot_adapter_opqbot-0.1.2.dist-info/WHEEL
nonebot_adapter_opqbot-0.1.2.dist-info/RECORD
